<Properties StartupConfiguration="{3291A079-5405-3748-6ED4-D5CA0D492CBF}|">
  <MonoDevelop.Ide.Workbench ActiveDocument="Assets/Scripts/Ball.cs">
    <Files>
      <File FileName="Assets/Scripts/Recycled Scripts/PlayerController.cs" Line="122" Column="49" />
      <File FileName="Assets/Scripts/Ball.cs" Line="30" Column="26" />
      <File FileName="Assets/Scripts/ScoreManager.cs" Line="8" Column="12" />
    </Files>
  </MonoDevelop.Ide.Workbench>
  <MonoDevelop.Ide.Workspace ActiveConfiguration="Debug" />
  <MonoDevelop.Ide.DebuggingService.Breakpoints>
    <BreakpointStore />
  </MonoDevelop.Ide.DebuggingService.Breakpoints>
  <MonoDevelop.Ide.DebuggingService.PinnedWatches />
  <MonoDevelop.Ide.ItemProperties.BeachBoyBlast PreferredExecutionTarget="Unity.Editor" />
  <MultiItemStartupConfigurations />
</Properties>